caluxPy_bc/CalculoPosicion.py
caluxPy_bc/CalculoPosicion2.py
caluxPy_bc/ExtPosMid.py
caluxPy_bc/ExtraccionBGD.py
caluxPy_bc/ExtraccionBGD2.py
caluxPy_bc/ExtraccionBGD3.py
caluxPy_bc/__initi__.py
caluxPy_bc-0.1.10.dist-info/LICENSE.txt
caluxPy_bc-0.1.10.dist-info/METADATA
caluxPy_bc-0.1.10.dist-info/WHEEL
caluxPy_bc-0.1.10.dist-info/top_level.txt
caluxPy_bc-0.1.10.dist-info/RECORD
