Metadata-Version: 2.1
Name: caluxPy_bc
Version: 0.1.10
Summary: Data Extraction Tool
Author-email: Luis Manuel Tavarez Valenzuela <luima2494@gmail.com>
Maintainer-email: Luis Manuel Tavarez Valenzuela <luima2494@gmail.com>
License: MIT License
Classifier: Programming Language :: Python :: 3
Classifier: License :: OSI Approved :: MIT License
Classifier: Operating System :: OS Independent
Requires-Python: >=3.11.4
License-File: LICENSE.txt
Requires-Dist: datetime>=5.3
Requires-Dist: numpy>=1.26.4
Requires-Dist: pandas>=2.2.0
Requires-Dist: openpyxl>=3.1.2
